Metadata-Version: 2.1
Name: great-talon
Version: 1.0.0
Summary: Mailgun library to extract message quotations and signatures.
Home-page: https://github.com/entamburini/talon
Author: Mailgun Inc. && entamburini
Author-email: entamburini@uc.cl
License: APACHE2
Platform: UNKNOWN
